{"saved_at": "2026-02-01T22:29:37.603672", "key": "quant_ui_state_v1", "value": {"theme": "dark", "activeTab": "pool", "stockCode": "300394.SZ", "stockName": "天孚通信", "initCapital": "100", "startDate": "2024-01-27", "endDate": "2026-01-30", "paramStrategy": "turtle_enhanced", "detailStrategy": "momentum_rotation", "comparisonStrategies": ["deep_fusion", "volume_breakout", "oversold_rebound", "trend_enhanced", "macd_divergence", "bollinger_extreme", "momentum_rotation", "turtle_enhanced"], "screeningStrategies": [], "screeningScope": "hot", "signalPeriod": "3", "customStockInput": "", "enableSmartVerification": false, "smartMinScore": "0", "smartMinReturn": "0", "smartMinWinRate": "0", "smartMinTrades": "0", "smartRankBy": "score", "enableIndustryFilter": false, "enableConceptFilter": false, "screeningIndustry": "", "screeningConcept": "", "selectedIndustries": [], "poolFilter": "", "optEnableTakeProfit": true, "optEnableStopLoss": true, "optEnableVolumeMulti": true, "optEnableDynamicTpCallback": true}}