{
  "quant_ui_state_v1": {
    "theme": "dark",
    "activeTab": "optimization",
    "stockName": "",
    "initCapital": "100",
    "paramStrategy": "turtle_enhanced",
    "detailStrategy": "turtle_enhanced",
    "comparisonStrategies": [
      "deep_fusion",
      "volume_breakout",
      "oversold_rebound",
      "trend_enhanced",
      "macd_divergence",
      "bollinger_extreme",
      "momentum_rotation",
      "turtle_enhanced"
    ],
    "screeningStrategies": [
      "deep_fusion",
      "volume_breakout",
      "oversold_rebound",
      "trend_enhanced",
      "macd_divergence",
      "bollinger_extreme",
      "momentum_rotation",
      "turtle_enhanced"
    ],
    "screeningScope": "all_a",
    "signalPeriod": "1",
    "customStockInput": "",
    "enableSmartVerification": false,
    "enableFundamentalFilter": true,
    "fundMinRoe": "8",
    "fundMinNetprofitYoy": "0",
    "fundMaxPe": "60",
    "fundMaxPb": "6",
    "fundMaxDebtToAssets": "70",
    "fundRequirePositiveOcf": true,
    "fundAllowNoData": false,
    "smartMinScore": "0",
    "smartMinReturn": "0",
    "smartMinWinRate": "0",
    "smartMinTrades": "0",
    "smartRankBy": "score",
    "enableIndustryFilter": false,
    "enableConceptFilter": false,
    "screeningIndustry": "",
    "screeningConcept": "",
    "selectedIndustries": [],
    "poolFilter": "",
    "optEnableTakeProfit": true,
    "optEnableStopLoss": true,
    "optEnableVolumeMulti": true,
    "optEnableDynamicTpCallback": true
  },
  "optimizationResults": {
    "bollinger_extreme": {
      "bestParams": {
        "bollDeviation": 2,
        "minConditions": 2,
        "rsiOversold": 30,
        "scoreThreshold": 60,
        "stopLoss": 0.08,
        "takeProfit": 0.18,
        "useBandWidthConfirm": true,
        "useCandleConfirm": true,
        "useLowerBandTouch": true,
        "useMaSupport": true,
        "useRsiConfirm": true,
        "useVolatilityAdjust": true,
        "useVolumeConfirm": true,
        "volumeMulti": 1.2
      },
      "industries": {
        "化工": {
          "bollDeviation": 2,
          "minConditions": 2,
          "rsiOversold": 30,
          "scoreThreshold": 60,
          "stopLoss": 0.08,
          "takeProfit": 0.08,
          "useBandWidthConfirm": true,
          "useCandleConfirm": true,
          "useLowerBandTouch": true,
          "useMaSupport": true,
          "useRsiConfirm": true,
          "useVolatilityAdjust": true,
          "useVolumeConfirm": true,
          "volumeMulti": 1.2
        },
        "医药": {
          "bollDeviation": 2,
          "minConditions": 2,
          "rsiOversold": 30,
          "scoreThreshold": 60,
          "stopLoss": 0.06,
          "takeProfit": 0.1,
          "useBandWidthConfirm": true,
          "useCandleConfirm": true,
          "useLowerBandTouch": true,
          "useMaSupport": true,
          "useRsiConfirm": true,
          "useVolatilityAdjust": true,
          "useVolumeConfirm": true,
          "volumeMulti": 1.2
        },
        "新能源": {
          "bollDeviation": 2,
          "minConditions": 2,
          "rsiOversold": 30,
          "scoreThreshold": 60,
          "stopLoss": 0.05,
          "takeProfit": 0.1,
          "useBandWidthConfirm": true,
          "useCandleConfirm": true,
          "useLowerBandTouch": true,
          "useMaSupport": true,
          "useRsiConfirm": true,
          "useVolatilityAdjust": true,
          "useVolumeConfirm": true,
          "volumeMulti": 1.2
        },
        "有色": {
          "bollDeviation": 2,
          "minConditions": 2,
          "rsiOversold": 30,
          "scoreThreshold": 60,
          "stopLoss": 0.03,
          "takeProfit": 0.12,
          "useBandWidthConfirm": true,
          "useCandleConfirm": true,
          "useLowerBandTouch": true,
          "useMaSupport": true,
          "useRsiConfirm": true,
          "useVolatilityAdjust": true,
          "useVolumeConfirm": true,
          "volumeMulti": 1.2
        },
        "电子": {
          "bollDeviation": 2,
          "minConditions": 2,
          "rsiOversold": 30,
          "scoreThreshold": 60,
          "stopLoss": 0.08,
          "takeProfit": 0.15,
          "useBandWidthConfirm": true,
          "useCandleConfirm": true,
          "useLowerBandTouch": true,
          "useMaSupport": true,
          "useRsiConfirm": true,
          "useVolatilityAdjust": true,
          "useVolumeConfirm": true,
          "volumeMulti": 1.2
        },
        "白酒": {
          "bollDeviation": 2,
          "minConditions": 2,
          "rsiOversold": 30,
          "scoreThreshold": 60,
          "stopLoss": 0.03,
          "takeProfit": 0.25,
          "useBandWidthConfirm": true,
          "useCandleConfirm": true,
          "useLowerBandTouch": true,
          "useMaSupport": true,
          "useRsiConfirm": true,
          "useVolatilityAdjust": true,
          "useVolumeConfirm": true,
          "volumeMulti": 1.2
        },
        "科技": {
          "bollDeviation": 2,
          "minConditions": 2,
          "rsiOversold": 30,
          "scoreThreshold": 60,
          "stopLoss": 0.12,
          "takeProfit": 0.08,
          "useBandWidthConfirm": true,
          "useCandleConfirm": true,
          "useLowerBandTouch": true,
          "useMaSupport": true,
          "useRsiConfirm": true,
          "useVolatilityAdjust": true,
          "useVolumeConfirm": true,
          "volumeMulti": 1.2
        },
        "银行": {
          "bollDeviation": 2,
          "minConditions": 2,
          "rsiOversold": 30,
          "scoreThreshold": 60,
          "stopLoss": 0.08,
          "takeProfit": 0.18,
          "useBandWidthConfirm": true,
          "useCandleConfirm": true,
          "useLowerBandTouch": true,
          "useMaSupport": true,
          "useRsiConfirm": true,
          "useVolatilityAdjust": true,
          "useVolumeConfirm": true,
          "volumeMulti": 1.2
        }
      }
    },
    "deep_fusion": {
      "bestParams": {
        "macdThreshold": 0,
        "minConfirmations": 3,
        "mlScoreThreshold": 55,
        "rsiThreshold": 35,
        "stopLoss": 0.1,
        "takeProfit": 0.1,
        "useAdxConfirm": true,
        "useMa5AboveMa20": true,
        "useMacdRising": true,
        "useMomentumConfirm": true,
        "usePriceAboveMa5": true,
        "usePriceBelowBoll": true,
        "useRsiBelow35": true,
        "useVolumeAboveMa": true,
        "volumeMulti": 1.5
      },
      "industries": {
        "化工": {
          "macdThreshold": 0,
          "minConfirmations": 3,
          "mlScoreThreshold": 55,
          "rsiThreshold": 35,
          "stopLoss": 0.12,
          "takeProfit": 0.08,
          "useAdxConfirm": true,
          "useMa5AboveMa20": true,
          "useMacdRising": true,
          "useMomentumConfirm": true,
          "usePriceAboveMa5": true,
          "usePriceBelowBoll": true,
          "useRsiBelow35": true,
          "useVolumeAboveMa": true,
          "volumeMulti": 1.5
        },
        "医药": {
          "macdThreshold": 0,
          "minConfirmations": 3,
          "mlScoreThreshold": 55,
          "rsiThreshold": 35,
          "stopLoss": 0.06,
          "takeProfit": 0.18,
          "useAdxConfirm": true,
          "useMa5AboveMa20": true,
          "useMacdRising": true,
          "useMomentumConfirm": true,
          "usePriceAboveMa5": true,
          "usePriceBelowBoll": true,
          "useRsiBelow35": true,
          "useVolumeAboveMa": true,
          "volumeMulti": 1.5
        },
        "新能源": {
          "macdThreshold": 0,
          "minConfirmations": 3,
          "mlScoreThreshold": 55,
          "rsiThreshold": 35,
          "stopLoss": 0.1,
          "takeProfit": 0.08,
          "useAdxConfirm": true,
          "useMa5AboveMa20": true,
          "useMacdRising": true,
          "useMomentumConfirm": true,
          "usePriceAboveMa5": true,
          "usePriceBelowBoll": true,
          "useRsiBelow35": true,
          "useVolumeAboveMa": true,
          "volumeMulti": 1.5
        },
        "有色": {
          "macdThreshold": 0,
          "minConfirmations": 3,
          "mlScoreThreshold": 55,
          "rsiThreshold": 35,
          "stopLoss": 0.15,
          "takeProfit": 0.08,
          "useAdxConfirm": true,
          "useMa5AboveMa20": true,
          "useMacdRising": true,
          "useMomentumConfirm": true,
          "usePriceAboveMa5": true,
          "usePriceBelowBoll": true,
          "useRsiBelow35": true,
          "useVolumeAboveMa": true,
          "volumeMulti": 1.5
        },
        "电子": {
          "macdThreshold": 0,
          "minConfirmations": 3,
          "mlScoreThreshold": 55,
          "rsiThreshold": 35,
          "stopLoss": 0.05,
          "takeProfit": 0.08,
          "useAdxConfirm": true,
          "useMa5AboveMa20": true,
          "useMacdRising": true,
          "useMomentumConfirm": true,
          "usePriceAboveMa5": true,
          "usePriceBelowBoll": true,
          "useRsiBelow35": true,
          "useVolumeAboveMa": true,
          "volumeMulti": 1.5
        },
        "白酒": {
          "macdThreshold": 0,
          "minConfirmations": 3,
          "mlScoreThreshold": 55,
          "rsiThreshold": 35,
          "stopLoss": 0.03,
          "takeProfit": 0.08,
          "useAdxConfirm": true,
          "useMa5AboveMa20": true,
          "useMacdRising": true,
          "useMomentumConfirm": true,
          "usePriceAboveMa5": true,
          "usePriceBelowBoll": true,
          "useRsiBelow35": true,
          "useVolumeAboveMa": true,
          "volumeMulti": 1.5
        },
        "科技": {
          "macdThreshold": 0,
          "minConfirmations": 3,
          "mlScoreThreshold": 55,
          "rsiThreshold": 35,
          "stopLoss": 0.08,
          "takeProfit": 0.1,
          "useAdxConfirm": true,
          "useMa5AboveMa20": true,
          "useMacdRising": true,
          "useMomentumConfirm": true,
          "usePriceAboveMa5": true,
          "usePriceBelowBoll": true,
          "useRsiBelow35": true,
          "useVolumeAboveMa": true,
          "volumeMulti": 1.5
        },
        "银行": {
          "macdThreshold": 0,
          "minConfirmations": 3,
          "mlScoreThreshold": 55,
          "rsiThreshold": 35,
          "stopLoss": 0.1,
          "takeProfit": 0.1,
          "useAdxConfirm": true,
          "useMa5AboveMa20": true,
          "useMacdRising": true,
          "useMomentumConfirm": true,
          "usePriceAboveMa5": true,
          "usePriceBelowBoll": true,
          "useRsiBelow35": true,
          "useVolumeAboveMa": true,
          "volumeMulti": 1.5
        }
      }
    },
    "macd_divergence": {
      "bestParams": {
        "lookbackPeriod": 30,
        "minConditions": 2,
        "scoreThreshold": 60,
        "stopLoss": 0.08,
        "takeProfit": 0.18,
        "useBullishDivergence": true,
        "useCandleConfirm": true,
        "useHistogramDivergence": true,
        "useMaConfirm": true,
        "useRsiDivergence": true,
        "useTrendFilter": true,
        "useVolumeDivergence": true,
        "volumeMulti": 1.2
      },
      "industries": {
        "化工": {
          "lookbackPeriod": 30,
          "minConditions": 2,
          "scoreThreshold": 60,
          "stopLoss": 0.05,
          "takeProfit": 0.08,
          "useBullishDivergence": true,
          "useCandleConfirm": true,
          "useHistogramDivergence": true,
          "useMaConfirm": true,
          "useRsiDivergence": true,
          "useTrendFilter": true,
          "useVolumeDivergence": true,
          "volumeMulti": 1.2
        },
        "医药": {
          "lookbackPeriod": 30,
          "minConditions": 2,
          "scoreThreshold": 60,
          "stopLoss": 0.05,
          "takeProfit": 0.1,
          "useBullishDivergence": true,
          "useCandleConfirm": true,
          "useHistogramDivergence": true,
          "useMaConfirm": true,
          "useRsiDivergence": true,
          "useTrendFilter": true,
          "useVolumeDivergence": true,
          "volumeMulti": 1.2
        },
        "新能源": {
          "lookbackPeriod": 30,
          "minConditions": 2,
          "scoreThreshold": 60,
          "stopLoss": 0.03,
          "takeProfit": 0.08,
          "useBullishDivergence": true,
          "useCandleConfirm": true,
          "useHistogramDivergence": true,
          "useMaConfirm": true,
          "useRsiDivergence": true,
          "useTrendFilter": true,
          "useVolumeDivergence": true,
          "volumeMulti": 1.2
        },
        "有色": {
          "lookbackPeriod": 30,
          "minConditions": 2,
          "scoreThreshold": 60,
          "stopLoss": 0.06,
          "takeProfit": 0.08,
          "useBullishDivergence": true,
          "useCandleConfirm": true,
          "useHistogramDivergence": true,
          "useMaConfirm": true,
          "useRsiDivergence": true,
          "useTrendFilter": true,
          "useVolumeDivergence": true,
          "volumeMulti": 1.2
        },
        "电子": {
          "lookbackPeriod": 30,
          "minConditions": 2,
          "scoreThreshold": 60,
          "stopLoss": 0.05,
          "takeProfit": 0.15,
          "useBullishDivergence": true,
          "useCandleConfirm": true,
          "useHistogramDivergence": true,
          "useMaConfirm": true,
          "useRsiDivergence": true,
          "useTrendFilter": true,
          "useVolumeDivergence": true,
          "volumeMulti": 1.2
        },
        "白酒": {
          "lookbackPeriod": 30,
          "minConditions": 2,
          "scoreThreshold": 60,
          "stopLoss": 0.12,
          "takeProfit": 0.18,
          "useBullishDivergence": true,
          "useCandleConfirm": true,
          "useHistogramDivergence": true,
          "useMaConfirm": true,
          "useRsiDivergence": true,
          "useTrendFilter": true,
          "useVolumeDivergence": true,
          "volumeMulti": 1.2
        },
        "科技": {
          "lookbackPeriod": 30,
          "minConditions": 2,
          "scoreThreshold": 60,
          "stopLoss": 0.05,
          "takeProfit": 0.08,
          "useBullishDivergence": true,
          "useCandleConfirm": true,
          "useHistogramDivergence": true,
          "useMaConfirm": true,
          "useRsiDivergence": true,
          "useTrendFilter": true,
          "useVolumeDivergence": true,
          "volumeMulti": 1.2
        },
        "银行": {
          "lookbackPeriod": 30,
          "minConditions": 2,
          "scoreThreshold": 60,
          "stopLoss": 0.08,
          "takeProfit": 0.18,
          "useBullishDivergence": true,
          "useCandleConfirm": true,
          "useHistogramDivergence": true,
          "useMaConfirm": true,
          "useRsiDivergence": true,
          "useTrendFilter": true,
          "useVolumeDivergence": true,
          "volumeMulti": 1.2
        }
      }
    },
    "momentum_rotation": {
      "bestParams": {
        "longMomentumPeriod": 60,
        "mediumMomentumPeriod": 20,
        "mediumMomentumThreshold": 5,
        "minConditions": 3,
        "scoreThreshold": 65,
        "shortMomentumPeriod": 10,
        "shortMomentumThreshold": 3,
        "stopLoss": 0.03,
        "takeProfit": 0.08,
        "useLongMomentum": true,
        "useMacdConfirm": true,
        "useMediumMomentum": true,
        "useMomentumQuality": true,
        "useRelativeStrength": true,
        "useShortMomentum": true,
        "useVolatilityAdjust": true,
        "useVolumeConfirm": true,
        "volumeMulti": 1.5
      },
      "industries": {
        "化工": {
          "longMomentumPeriod": 60,
          "mediumMomentumPeriod": 20,
          "mediumMomentumThreshold": 5,
          "minConditions": 3,
          "scoreThreshold": 65,
          "shortMomentumPeriod": 10,
          "shortMomentumThreshold": 3,
          "stopLoss": 0.03,
          "takeProfit": 0.1,
          "useLongMomentum": true,
          "useMacdConfirm": true,
          "useMediumMomentum": true,
          "useMomentumQuality": true,
          "useRelativeStrength": true,
          "useShortMomentum": true,
          "useVolatilityAdjust": true,
          "useVolumeConfirm": true,
          "volumeMulti": 1.5
        },
        "医药": {
          "longMomentumPeriod": 60,
          "mediumMomentumPeriod": 20,
          "mediumMomentumThreshold": 5,
          "minConditions": 3,
          "scoreThreshold": 65,
          "shortMomentumPeriod": 10,
          "shortMomentumThreshold": 3,
          "stopLoss": 0.05,
          "takeProfit": 0.15,
          "useLongMomentum": true,
          "useMacdConfirm": true,
          "useMediumMomentum": true,
          "useMomentumQuality": true,
          "useRelativeStrength": true,
          "useShortMomentum": true,
          "useVolatilityAdjust": true,
          "useVolumeConfirm": true,
          "volumeMulti": 1.5
        },
        "新能源": {
          "longMomentumPeriod": 60,
          "mediumMomentumPeriod": 20,
          "mediumMomentumThreshold": 5,
          "minConditions": 3,
          "scoreThreshold": 65,
          "shortMomentumPeriod": 10,
          "shortMomentumThreshold": 3,
          "stopLoss": 0.03,
          "takeProfit": 0.08,
          "useLongMomentum": true,
          "useMacdConfirm": true,
          "useMediumMomentum": true,
          "useMomentumQuality": true,
          "useRelativeStrength": true,
          "useShortMomentum": true,
          "useVolatilityAdjust": true,
          "useVolumeConfirm": true,
          "volumeMulti": 1.5
        },
        "有色": {
          "longMomentumPeriod": 60,
          "mediumMomentumPeriod": 20,
          "mediumMomentumThreshold": 5,
          "minConditions": 3,
          "scoreThreshold": 65,
          "shortMomentumPeriod": 10,
          "shortMomentumThreshold": 3,
          "stopLoss": 0.03,
          "takeProfit": 0.12,
          "useLongMomentum": true,
          "useMacdConfirm": true,
          "useMediumMomentum": true,
          "useMomentumQuality": true,
          "useRelativeStrength": true,
          "useShortMomentum": true,
          "useVolatilityAdjust": true,
          "useVolumeConfirm": true,
          "volumeMulti": 1.5
        },
        "电子": {
          "longMomentumPeriod": 60,
          "mediumMomentumPeriod": 20,
          "mediumMomentumThreshold": 5,
          "minConditions": 3,
          "scoreThreshold": 65,
          "shortMomentumPeriod": 10,
          "shortMomentumThreshold": 3,
          "stopLoss": 0.12,
          "takeProfit": 0.08,
          "useLongMomentum": true,
          "useMacdConfirm": true,
          "useMediumMomentum": true,
          "useMomentumQuality": true,
          "useRelativeStrength": true,
          "useShortMomentum": true,
          "useVolatilityAdjust": true,
          "useVolumeConfirm": true,
          "volumeMulti": 1.5
        },
        "白酒": {
          "longMomentumPeriod": 60,
          "mediumMomentumPeriod": 20,
          "mediumMomentumThreshold": 5,
          "minConditions": 3,
          "scoreThreshold": 65,
          "shortMomentumPeriod": 10,
          "shortMomentumThreshold": 3,
          "stopLoss": 0.03,
          "takeProfit": 0.08,
          "useLongMomentum": true,
          "useMacdConfirm": true,
          "useMediumMomentum": true,
          "useMomentumQuality": true,
          "useRelativeStrength": true,
          "useShortMomentum": true,
          "useVolatilityAdjust": true,
          "useVolumeConfirm": true,
          "volumeMulti": 1.5
        },
        "科技": {
          "longMomentumPeriod": 60,
          "mediumMomentumPeriod": 20,
          "mediumMomentumThreshold": 5,
          "minConditions": 3,
          "scoreThreshold": 65,
          "shortMomentumPeriod": 10,
          "shortMomentumThreshold": 3,
          "stopLoss": 0.1,
          "takeProfit": 0.1,
          "useLongMomentum": true,
          "useMacdConfirm": true,
          "useMediumMomentum": true,
          "useMomentumQuality": true,
          "useRelativeStrength": true,
          "useShortMomentum": true,
          "useVolatilityAdjust": true,
          "useVolumeConfirm": true,
          "volumeMulti": 1.5
        },
        "银行": {
          "longMomentumPeriod": 60,
          "mediumMomentumPeriod": 20,
          "mediumMomentumThreshold": 5,
          "minConditions": 3,
          "scoreThreshold": 65,
          "shortMomentumPeriod": 10,
          "shortMomentumThreshold": 3,
          "stopLoss": 0.03,
          "takeProfit": 0.08,
          "useLongMomentum": true,
          "useMacdConfirm": true,
          "useMediumMomentum": true,
          "useMomentumQuality": true,
          "useRelativeStrength": true,
          "useShortMomentum": true,
          "useVolatilityAdjust": true,
          "useVolumeConfirm": true,
          "volumeMulti": 1.5
        }
      }
    },
    "oversold_rebound": {
      "bestParams": {
        "bollingerOffset": 0.02,
        "minConditions": 3,
        "nearLowRatio": 1.03,
        "rsiOversold": 30,
        "scoreThreshold": 65,
        "stopLoss": 0.1,
        "takeProfit": 0.18,
        "useCandlePattern": true,
        "useMacdDivergence": true,
        "useNearLow": true,
        "useRsiOversold": true,
        "useTouchLowerBoll": true,
        "useTrendFilter": true,
        "useVolumePattern": true,
        "volumeMulti": 1.2
      },
      "industries": {
        "化工": {
          "bollingerOffset": 0.02,
          "minConditions": 3,
          "nearLowRatio": 1.03,
          "rsiOversold": 30,
          "scoreThreshold": 65,
          "stopLoss": 0.05,
          "takeProfit": 0.08,
          "useCandlePattern": true,
          "useMacdDivergence": true,
          "useNearLow": true,
          "useRsiOversold": true,
          "useTouchLowerBoll": true,
          "useTrendFilter": true,
          "useVolumePattern": true,
          "volumeMulti": 1.2
        },
        "医药": {
          "bollingerOffset": 0.02,
          "minConditions": 3,
          "nearLowRatio": 1.03,
          "rsiOversold": 30,
          "scoreThreshold": 65,
          "stopLoss": 0.06,
          "takeProfit": 0.1,
          "useCandlePattern": true,
          "useMacdDivergence": true,
          "useNearLow": true,
          "useRsiOversold": true,
          "useTouchLowerBoll": true,
          "useTrendFilter": true,
          "useVolumePattern": true,
          "volumeMulti": 1.2
        },
        "新能源": {
          "bollingerOffset": 0.02,
          "minConditions": 3,
          "nearLowRatio": 1.03,
          "rsiOversold": 30,
          "scoreThreshold": 65,
          "stopLoss": 0.06,
          "takeProfit": 0.15,
          "useCandlePattern": true,
          "useMacdDivergence": true,
          "useNearLow": true,
          "useRsiOversold": true,
          "useTouchLowerBoll": true,
          "useTrendFilter": true,
          "useVolumePattern": true,
          "volumeMulti": 1.2
        },
        "有色": {
          "bollingerOffset": 0.02,
          "minConditions": 3,
          "nearLowRatio": 1.03,
          "rsiOversold": 30,
          "scoreThreshold": 65,
          "stopLoss": 0.08,
          "takeProfit": 0.12,
          "useCandlePattern": true,
          "useMacdDivergence": true,
          "useNearLow": true,
          "useRsiOversold": true,
          "useTouchLowerBoll": true,
          "useTrendFilter": true,
          "useVolumePattern": true,
          "volumeMulti": 1.2
        },
        "电子": {
          "bollingerOffset": 0.02,
          "minConditions": 3,
          "nearLowRatio": 1.03,
          "rsiOversold": 30,
          "scoreThreshold": 65,
          "stopLoss": 0.05,
          "takeProfit": 0.15,
          "useCandlePattern": true,
          "useMacdDivergence": true,
          "useNearLow": true,
          "useRsiOversold": true,
          "useTouchLowerBoll": true,
          "useTrendFilter": true,
          "useVolumePattern": true,
          "volumeMulti": 1.2
        },
        "白酒": {
          "bollingerOffset": 0.02,
          "minConditions": 3,
          "nearLowRatio": 1.03,
          "rsiOversold": 30,
          "scoreThreshold": 65,
          "stopLoss": 0.1,
          "takeProfit": 0.25,
          "useCandlePattern": true,
          "useMacdDivergence": true,
          "useNearLow": true,
          "useRsiOversold": true,
          "useTouchLowerBoll": true,
          "useTrendFilter": true,
          "useVolumePattern": true,
          "volumeMulti": 1.2
        },
        "科技": {
          "bollingerOffset": 0.02,
          "minConditions": 3,
          "nearLowRatio": 1.03,
          "rsiOversold": 30,
          "scoreThreshold": 65,
          "stopLoss": 0.12,
          "takeProfit": 0.1,
          "useCandlePattern": true,
          "useMacdDivergence": true,
          "useNearLow": true,
          "useRsiOversold": true,
          "useTouchLowerBoll": true,
          "useTrendFilter": true,
          "useVolumePattern": true,
          "volumeMulti": 1.2
        },
        "银行": {
          "bollingerOffset": 0.02,
          "minConditions": 3,
          "nearLowRatio": 1.03,
          "rsiOversold": 30,
          "scoreThreshold": 65,
          "stopLoss": 0.1,
          "takeProfit": 0.18,
          "useCandlePattern": true,
          "useMacdDivergence": true,
          "useNearLow": true,
          "useRsiOversold": true,
          "useTouchLowerBoll": true,
          "useTrendFilter": true,
          "useVolumePattern": true,
          "volumeMulti": 1.2
        }
      }
    },
    "trend_enhanced": {
      "bestParams": {
        "macdThreshold": 0,
        "minConditions": 3,
        "scoreThreshold": 70,
        "stopLoss": 0.1,
        "takeProfit": 0.1,
        "useAdxConfirm": true,
        "useBollConfirm": true,
        "useMacdPositive": true,
        "useMomentumConfirm": true,
        "usePriceAboveMa": true,
        "useShortMaAlignment": true,
        "useTrendPersistence": true,
        "useVolumeConfirm": true,
        "volumeMulti": 1.2
      },
      "industries": {
        "化工": {
          "macdThreshold": 0,
          "minConditions": 3,
          "scoreThreshold": 70,
          "stopLoss": 0.06,
          "takeProfit": 0.1,
          "useAdxConfirm": true,
          "useBollConfirm": true,
          "useMacdPositive": true,
          "useMomentumConfirm": true,
          "usePriceAboveMa": true,
          "useShortMaAlignment": true,
          "useTrendPersistence": true,
          "useVolumeConfirm": true,
          "volumeMulti": 1.2
        },
        "医药": {
          "macdThreshold": 0,
          "minConditions": 3,
          "scoreThreshold": 70,
          "stopLoss": 0.15,
          "takeProfit": 0.08,
          "useAdxConfirm": true,
          "useBollConfirm": true,
          "useMacdPositive": true,
          "useMomentumConfirm": true,
          "usePriceAboveMa": true,
          "useShortMaAlignment": true,
          "useTrendPersistence": true,
          "useVolumeConfirm": true,
          "volumeMulti": 1.2
        },
        "新能源": {
          "macdThreshold": 0,
          "minConditions": 3,
          "scoreThreshold": 70,
          "stopLoss": 0.08,
          "takeProfit": 0.1,
          "useAdxConfirm": true,
          "useBollConfirm": true,
          "useMacdPositive": true,
          "useMomentumConfirm": true,
          "usePriceAboveMa": true,
          "useShortMaAlignment": true,
          "useTrendPersistence": true,
          "useVolumeConfirm": true,
          "volumeMulti": 1.2
        },
        "有色": {
          "macdThreshold": 0,
          "minConditions": 3,
          "scoreThreshold": 70,
          "stopLoss": 0.12,
          "takeProfit": 0.08,
          "useAdxConfirm": true,
          "useBollConfirm": true,
          "useMacdPositive": true,
          "useMomentumConfirm": true,
          "usePriceAboveMa": true,
          "useShortMaAlignment": true,
          "useTrendPersistence": true,
          "useVolumeConfirm": true,
          "volumeMulti": 1.2
        },
        "电子": {
          "macdThreshold": 0,
          "minConditions": 3,
          "scoreThreshold": 70,
          "stopLoss": 0.06,
          "takeProfit": 0.15,
          "useAdxConfirm": true,
          "useBollConfirm": true,
          "useMacdPositive": true,
          "useMomentumConfirm": true,
          "usePriceAboveMa": true,
          "useShortMaAlignment": true,
          "useTrendPersistence": true,
          "useVolumeConfirm": true,
          "volumeMulti": 1.2
        },
        "白酒": {
          "macdThreshold": 0,
          "minConditions": 3,
          "scoreThreshold": 70,
          "stopLoss": 0.08,
          "takeProfit": 0.25,
          "useAdxConfirm": true,
          "useBollConfirm": true,
          "useMacdPositive": true,
          "useMomentumConfirm": true,
          "usePriceAboveMa": true,
          "useShortMaAlignment": true,
          "useTrendPersistence": true,
          "useVolumeConfirm": true,
          "volumeMulti": 1.2
        },
        "科技": {
          "macdThreshold": 0,
          "minConditions": 3,
          "scoreThreshold": 70,
          "stopLoss": 0.08,
          "takeProfit": 0.1,
          "useAdxConfirm": true,
          "useBollConfirm": true,
          "useMacdPositive": true,
          "useMomentumConfirm": true,
          "usePriceAboveMa": true,
          "useShortMaAlignment": true,
          "useTrendPersistence": true,
          "useVolumeConfirm": true,
          "volumeMulti": 1.2
        },
        "银行": {
          "macdThreshold": 0,
          "minConditions": 3,
          "scoreThreshold": 70,
          "stopLoss": 0.1,
          "takeProfit": 0.1,
          "useAdxConfirm": true,
          "useBollConfirm": true,
          "useMacdPositive": true,
          "useMomentumConfirm": true,
          "usePriceAboveMa": true,
          "useShortMaAlignment": true,
          "useTrendPersistence": true,
          "useVolumeConfirm": true,
          "volumeMulti": 1.2
        }
      }
    },
    "turtle_enhanced": {
      "bestParams": {
        "atrMultiplier": 2,
        "entryPeriod": 20,
        "exitPeriod": 10,
        "minConditions": 3,
        "scoreThreshold": 65,
        "stopLoss": 0.12,
        "takeProfit": 0.15,
        "useAdxConfirm": true,
        "useBreakoutEntry": true,
        "useFalseBreakoutFilter": true,
        "useRiskManagement": true,
        "useSentimentFilter": true,
        "useTrendFilter": true,
        "useVolatilityFilter": true,
        "useVolumeConfirm": true,
        "volumeMulti": 1.5
      },
      "industries": {
        "化工": {
          "atrMultiplier": 2,
          "entryPeriod": 20,
          "exitPeriod": 10,
          "minConditions": 3,
          "scoreThreshold": 65,
          "stopLoss": 0.12,
          "takeProfit": 0.08,
          "useAdxConfirm": true,
          "useBreakoutEntry": true,
          "useFalseBreakoutFilter": true,
          "useRiskManagement": true,
          "useSentimentFilter": true,
          "useTrendFilter": true,
          "useVolatilityFilter": true,
          "useVolumeConfirm": true,
          "volumeMulti": 1.5
        },
        "医药": {
          "atrMultiplier": 2,
          "entryPeriod": 20,
          "exitPeriod": 10,
          "minConditions": 3,
          "scoreThreshold": 65,
          "stopLoss": 0.06,
          "takeProfit": 0.08,
          "useAdxConfirm": true,
          "useBreakoutEntry": true,
          "useFalseBreakoutFilter": true,
          "useRiskManagement": true,
          "useSentimentFilter": true,
          "useTrendFilter": true,
          "useVolatilityFilter": true,
          "useVolumeConfirm": true,
          "volumeMulti": 1.5
        },
        "新能源": {
          "atrMultiplier": 2,
          "entryPeriod": 20,
          "exitPeriod": 10,
          "minConditions": 3,
          "scoreThreshold": 65,
          "stopLoss": 0.08,
          "takeProfit": 0.1,
          "useAdxConfirm": true,
          "useBreakoutEntry": true,
          "useFalseBreakoutFilter": true,
          "useRiskManagement": true,
          "useSentimentFilter": true,
          "useTrendFilter": true,
          "useVolatilityFilter": true,
          "useVolumeConfirm": true,
          "volumeMulti": 1.5
        },
        "有色": {
          "atrMultiplier": 2,
          "entryPeriod": 20,
          "exitPeriod": 10,
          "minConditions": 3,
          "scoreThreshold": 65,
          "stopLoss": 0.03,
          "takeProfit": 0.1,
          "useAdxConfirm": true,
          "useBreakoutEntry": true,
          "useFalseBreakoutFilter": true,
          "useRiskManagement": true,
          "useSentimentFilter": true,
          "useTrendFilter": true,
          "useVolatilityFilter": true,
          "useVolumeConfirm": true,
          "volumeMulti": 1.5
        },
        "电子": {
          "atrMultiplier": 2,
          "entryPeriod": 20,
          "exitPeriod": 10,
          "minConditions": 3,
          "scoreThreshold": 65,
          "stopLoss": 0.08,
          "takeProfit": 0.12,
          "useAdxConfirm": true,
          "useBreakoutEntry": true,
          "useFalseBreakoutFilter": true,
          "useRiskManagement": true,
          "useSentimentFilter": true,
          "useTrendFilter": true,
          "useVolatilityFilter": true,
          "useVolumeConfirm": true,
          "volumeMulti": 1.5
        },
        "白酒": {
          "atrMultiplier": 2,
          "entryPeriod": 20,
          "exitPeriod": 10,
          "minConditions": 3,
          "scoreThreshold": 65,
          "stopLoss": 0.03,
          "takeProfit": 0.2,
          "useAdxConfirm": true,
          "useBreakoutEntry": true,
          "useFalseBreakoutFilter": true,
          "useRiskManagement": true,
          "useSentimentFilter": true,
          "useTrendFilter": true,
          "useVolatilityFilter": true,
          "useVolumeConfirm": true,
          "volumeMulti": 1.5
        },
        "科技": {
          "atrMultiplier": 2,
          "entryPeriod": 20,
          "exitPeriod": 10,
          "minConditions": 3,
          "scoreThreshold": 65,
          "stopLoss": 0.08,
          "takeProfit": 0.1,
          "useAdxConfirm": true,
          "useBreakoutEntry": true,
          "useFalseBreakoutFilter": true,
          "useRiskManagement": true,
          "useSentimentFilter": true,
          "useTrendFilter": true,
          "useVolatilityFilter": true,
          "useVolumeConfirm": true,
          "volumeMulti": 1.5
        },
        "银行": {
          "atrMultiplier": 2,
          "entryPeriod": 20,
          "exitPeriod": 10,
          "minConditions": 3,
          "scoreThreshold": 65,
          "stopLoss": 0.12,
          "takeProfit": 0.15,
          "useAdxConfirm": true,
          "useBreakoutEntry": true,
          "useFalseBreakoutFilter": true,
          "useRiskManagement": true,
          "useSentimentFilter": true,
          "useTrendFilter": true,
          "useVolatilityFilter": true,
          "useVolumeConfirm": true,
          "volumeMulti": 1.5
        }
      }
    },
    "volume_breakout": {
      "bestParams": {
        "breakoutPeriod": 20,
        "minConditions": 3,
        "rsiMax": 70,
        "scoreThreshold": 70,
        "stopLoss": 0.05,
        "takeProfit": 0.1,
        "useBullishCandle": true,
        "useChipConfirm": true,
        "useMomentumConfirm": true,
        "usePriceBreakout": true,
        "useTrendConfirm": true,
        "useVolatilityConfirm": true,
        "useVolumeUp": true,
        "volumeMulti": 2
      },
      "industries": {
        "化工": {
          "breakoutPeriod": 20,
          "minConditions": 3,
          "rsiMax": 70,
          "scoreThreshold": 70,
          "stopLoss": 0.03,
          "takeProfit": 0.08,
          "useBullishCandle": true,
          "useChipConfirm": true,
          "useMomentumConfirm": true,
          "usePriceBreakout": true,
          "useTrendConfirm": true,
          "useVolatilityConfirm": true,
          "useVolumeUp": true,
          "volumeMulti": 2
        },
        "医药": {
          "breakoutPeriod": 20,
          "minConditions": 3,
          "rsiMax": 70,
          "scoreThreshold": 70,
          "stopLoss": 0.05,
          "takeProfit": 0.12,
          "useBullishCandle": true,
          "useChipConfirm": true,
          "useMomentumConfirm": true,
          "usePriceBreakout": true,
          "useTrendConfirm": true,
          "useVolatilityConfirm": true,
          "useVolumeUp": true,
          "volumeMulti": 2
        },
        "新能源": {
          "breakoutPeriod": 20,
          "minConditions": 3,
          "rsiMax": 70,
          "scoreThreshold": 70,
          "stopLoss": 0.15,
          "takeProfit": 0.08,
          "useBullishCandle": true,
          "useChipConfirm": true,
          "useMomentumConfirm": true,
          "usePriceBreakout": true,
          "useTrendConfirm": true,
          "useVolatilityConfirm": true,
          "useVolumeUp": true,
          "volumeMulti": 2
        },
        "有色": {
          "breakoutPeriod": 20,
          "minConditions": 3,
          "rsiMax": 70,
          "scoreThreshold": 70,
          "stopLoss": 0.03,
          "takeProfit": 0.12,
          "useBullishCandle": true,
          "useChipConfirm": true,
          "useMomentumConfirm": true,
          "usePriceBreakout": true,
          "useTrendConfirm": true,
          "useVolatilityConfirm": true,
          "useVolumeUp": true,
          "volumeMulti": 2
        },
        "电子": {
          "breakoutPeriod": 20,
          "minConditions": 3,
          "rsiMax": 70,
          "scoreThreshold": 70,
          "stopLoss": 0.03,
          "takeProfit": 0.08,
          "useBullishCandle": true,
          "useChipConfirm": true,
          "useMomentumConfirm": true,
          "usePriceBreakout": true,
          "useTrendConfirm": true,
          "useVolatilityConfirm": true,
          "useVolumeUp": true,
          "volumeMulti": 2
        },
        "白酒": {
          "breakoutPeriod": 20,
          "minConditions": 3,
          "rsiMax": 70,
          "scoreThreshold": 70,
          "stopLoss": 0.03,
          "takeProfit": 0.1,
          "useBullishCandle": true,
          "useChipConfirm": true,
          "useMomentumConfirm": true,
          "usePriceBreakout": true,
          "useTrendConfirm": true,
          "useVolatilityConfirm": true,
          "useVolumeUp": true,
          "volumeMulti": 2
        },
        "科技": {
          "breakoutPeriod": 20,
          "minConditions": 3,
          "rsiMax": 70,
          "scoreThreshold": 70,
          "stopLoss": 0.03,
          "takeProfit": 0.1,
          "useBullishCandle": true,
          "useChipConfirm": true,
          "useMomentumConfirm": true,
          "usePriceBreakout": true,
          "useTrendConfirm": true,
          "useVolatilityConfirm": true,
          "useVolumeUp": true,
          "volumeMulti": 2
        },
        "银行": {
          "breakoutPeriod": 20,
          "minConditions": 3,
          "rsiMax": 70,
          "scoreThreshold": 70,
          "stopLoss": 0.05,
          "takeProfit": 0.1,
          "useBullishCandle": true,
          "useChipConfirm": true,
          "useMomentumConfirm": true,
          "usePriceBreakout": true,
          "useTrendConfirm": true,
          "useVolatilityConfirm": true,
          "useVolumeUp": true,
          "volumeMulti": 2
        }
      }
    }
  },
  "strategyConfig": {
    "takeProfit": 0.2,
    "stopLoss": 0.1,
    "volumeMulti": 1.5,
    "buyCooldown": 2,
    "useMa5Sell": true,
    "useDynamicTP": true,
    "useAdaptPosition": true,
    "enableTrendReentry": true,
    "dynamicTpThreshold": 0.1,
    "dynamicTpCallback": 0.03,
    "dynamicTpVariation": 0.15,
    "useAtrTrail": true,
    "atrTrailMinProfit": 0.06,
    "atrTrailMult": 2.5,
    "enableSwingTopSell": true,
    "swingSellRsi": 75,
    "swingSellNearHighPct": 0.02,
    "enableTrendFilter": true,
    "enableVolRatioFilter": true,
    "minSignalStrength": 0,
    "minVolRatio": 1.05,
    "trendSlopeLookback": 5,
    "reentryMinVolRatio": 0.95,
    "reentryMinRsi": 45,
    "reentryStrength": 62,
    "enableSwingBottomBuy": true,
    "swingBuyRsi": 35,
    "swingBuyNearLowPct": 0.02,
    "swingBuyMinVolRatio": 0.8,
    "swingBuyStrength": 62,
    "useStopLoss": true,
    "useTakeProfit": true,
    "useMacdDeathCross": true,
    "useRsiOverbought": true,
    "useHoldTimeout": true,
    "holdTimeoutDays": 30,
    "useMa5AboveMa20": true,
    "usePriceAboveMa5": true,
    "useMacdRising": true,
    "useRsiBelow35": true,
    "useRsiBelow25": true,
    "useVolumeAboveMa": true,
    "usePriceBelowBoll": true,
    "useNearLow": true,
    "useVolumeUp": true,
    "useRsiOversold": true,
    "useBullishCandle": true,
    "useGoldenCross": true,
    "useMacdPositive": true,
    "useBreakHigh": true,
    "useVolumeConfirm": true,
    "useTouchLowerBoll": true,
    "useMomentumFactor": true,
    "useValueFactor": true,
    "useQualityFactor": true,
    "strategySpecificConfig": {
      "bollinger_extreme": {
        "dynamicTpCallback": 0.05,
        "dynamicTpThreshold": 0.1,
        "dynamicTpVariation": 0.1,
        "stopLoss": 0.08,
        "takeProfit": 0.18,
        "useMa5Sell": false,
        "useRsiOverbought": false,
        "volumeMulti": 1.2
      },
      "deep_fusion": {
        "dynamicTpCallback": 0.06,
        "dynamicTpThreshold": 0.1,
        "dynamicTpVariation": 0.1,
        "stopLoss": 0.1,
        "takeProfit": 0.1,
        "useMa5Sell": false,
        "useRsiOverbought": false,
        "volumeMulti": 1.5
      },
      "macd_divergence": {
        "dynamicTpCallback": 0.06,
        "dynamicTpThreshold": 0.1,
        "dynamicTpVariation": 0.1,
        "stopLoss": 0.08,
        "takeProfit": 0.18,
        "useMa5Sell": false,
        "useRsiOverbought": false,
        "volumeMulti": 1.2
      },
      "momentum_rotation": {
        "dynamicTpCallback": 0.05,
        "dynamicTpThreshold": 0.1,
        "dynamicTpVariation": 0.1,
        "stopLoss": 0.03,
        "takeProfit": 0.08,
        "useMa5Sell": false,
        "useRsiOverbought": false,
        "volumeMulti": 1.5
      },
      "oversold_rebound": {
        "dynamicTpCallback": 0.05,
        "dynamicTpThreshold": 0.1,
        "dynamicTpVariation": 0.1,
        "stopLoss": 0.1,
        "takeProfit": 0.18,
        "useMa5Sell": false,
        "useRsiOverbought": false,
        "volumeMulti": 1.2
      },
      "trend_enhanced": {
        "dynamicTpCallback": 0.05,
        "dynamicTpThreshold": 0.1,
        "dynamicTpVariation": 0.1,
        "stopLoss": 0.1,
        "takeProfit": 0.1,
        "useMa5Sell": false,
        "useRsiOverbought": false,
        "volumeMulti": 1.2
      },
      "turtle_enhanced": {
        "dynamicTpCallback": 0.05,
        "dynamicTpThreshold": 0.1,
        "dynamicTpVariation": 0.1,
        "stopLoss": 0.12,
        "takeProfit": 0.15,
        "useMa5Sell": false,
        "useRsiOverbought": false,
        "volumeMulti": 1.5
      },
      "volume_breakout": {
        "dynamicTpCallback": 0.05,
        "dynamicTpThreshold": 0.1,
        "dynamicTpVariation": 0.1,
        "stopLoss": 0.05,
        "takeProfit": 0.1,
        "useMa5Sell": false,
        "useRsiOverbought": false,
        "volumeMulti": 2
      }
    }
  },
  "stockPool": []
}